{
  "traits": [
    { "trait": "Honest", "description": "Always tells the truth, even when it's inconvenient" },
    { "trait": "Deceitful", "description": "Lies frequently and manipulates others" },
    { "trait": "Brave", "description": "Faces danger without hesitation" },
    { "trait": "Cowardly", "description": "Avoids conflict and danger at all costs" },
    { "trait": "Generous", "description": "Freely gives to others without expecting return" },
    { "trait": "Greedy", "description": "Always seeks more wealth and possessions" },
    { "trait": "Kind", "description": "Shows compassion and care for others" },
    { "trait": "Cruel", "description": "Takes pleasure in others' suffering" },
    { "trait": "Humble", "description": "Modest about their abilities and status" },
    { "trait": "Arrogant", "description": "Believes they are superior to others" },
    { "trait": "Patient", "description": "Willing to wait and think things through" },
    { "trait": "Impulsive", "description": "Acts without thinking" },
    { "trait": "Loyal", "description": "Stands by friends and allies no matter what" },
    { "trait": "Treacherous", "description": "Will betray others for personal gain" },
    { "trait": "Optimistic", "description": "Always sees the bright side" },
    { "trait": "Pessimistic", "description": "Expects the worst outcome" },
    { "trait": "Curious", "description": "Eager to learn and explore" },
    { "trait": "Indifferent", "description": "Shows little interest in anything" },
    { "trait": "Ambitious", "description": "Driven to achieve great things" },
    { "trait": "Content", "description": "Satisfied with their current lot in life" },
    { "trait": "Suspicious", "description": "Distrusts others' motives" },
    { "trait": "Trusting", "description": "Believes the best of people" },
    { "trait": "Stubborn", "description": "Refuses to change their mind once set" },
    { "trait": "Flexible", "description": "Easily adapts to new situations" },
    { "trait": "Serious", "description": "Rarely jokes or shows levity" },
    { "trait": "Jovial", "description": "Always ready with a laugh or smile" },
    { "trait": "Protective", "description": "Fiercely guards those they care about" },
    { "trait": "Selfish", "description": "Puts their own needs first always" },
    { "trait": "Forgiving", "description": "Lets go of grudges easily" },
    { "trait": "Vengeful", "description": "Never forgets a slight" },
    { "trait": "Cautious", "description": "Carefully weighs risks before acting" },
    { "trait": "Reckless", "description": "Throws caution to the wind" }
  ],
  "mannerisms": [
    "Speaks in a whisper",
    "Speaks loudly and boisterously",
    "Uses long, elaborate words",
    "Speaks in short, clipped sentences",
    "Frequently uses a particular phrase or saying",
    "Stutters when nervous",
    "Has a distinctive laugh",
    "Never makes eye contact",
    "Stares intensely when speaking",
    "Fidgets constantly",
    "Stands perfectly still",
    "Paces when talking",
    "Gestures wildly while speaking",
    "Keeps hands clasped or hidden",
    "Touches their face frequently",
    "Drums fingers when impatient",
    "Hums or whistles absently",
    "Clears throat frequently",
    "Speaks with a foreign accent",
    "Uses outdated or formal speech",
    "Prone to tangents and rambling",
    "Gets straight to the point",
    "Asks many questions",
    "Rarely asks questions",
    "Laughs at inappropriate moments",
    "Never laughs",
    "Frequently sighs",
    "Sniffs or smells things",
    "Squints when thinking",
    "Tilts head when listening",
    "Interrupts others",
    "Waits patiently for others to finish"
  ],
  "motivations": [
    { "motivation": "Wealth", "description": "Driven by the desire for money and riches" },
    { "motivation": "Power", "description": "Seeks control over others or situations" },
    { "motivation": "Knowledge", "description": "Pursues understanding and learning" },
    { "motivation": "Fame", "description": "Wants to be known and remembered" },
    { "motivation": "Love", "description": "Driven by romantic or familial love" },
    { "motivation": "Revenge", "description": "Seeks to right a past wrong" },
    { "motivation": "Justice", "description": "Wants to see wrongdoers punished" },
    { "motivation": "Freedom", "description": "Values independence above all" },
    { "motivation": "Security", "description": "Seeks safety for self and loved ones" },
    { "motivation": "Faith", "description": "Devoted to a deity or cause" },
    { "motivation": "Duty", "description": "Bound by obligation or oath" },
    { "motivation": "Pleasure", "description": "Pursues enjoyment and comfort" },
    { "motivation": "Discovery", "description": "Wants to explore and find new things" },
    { "motivation": "Redemption", "description": "Seeks to atone for past mistakes" },
    { "motivation": "Protection", "description": "Driven to keep others safe" },
    { "motivation": "Legacy", "description": "Wants to leave something behind" },
    { "motivation": "Survival", "description": "Focused on staying alive" },
    { "motivation": "Belonging", "description": "Seeks acceptance and community" },
    { "motivation": "Respect", "description": "Wants to be taken seriously" },
    { "motivation": "Creativity", "description": "Driven to make and create things" }
  ],
  "fears": [
    "Death",
    "Being forgotten",
    "Losing loved ones",
    "Failure",
    "Betrayal",
    "The dark",
    "Heights",
    "Enclosed spaces",
    "Deep water",
    "Fire",
    "Magic",
    "Monsters",
    "Being alone",
    "Crowds",
    "Authority figures",
    "Poverty",
    "Illness",
    "Losing control",
    "The unknown",
    "Specific creature type",
    "A particular person",
    "Prophecy or fate",
    "Their own past",
    "Supernatural beings",
    "Public humiliation"
  ],
  "secrets": [
    "Has a forbidden love",
    "Committed a crime in the past",
    "Is not who they claim to be",
    "Has a hidden addiction",
    "Knows a dangerous secret about someone powerful",
    "Is secretly wealthy",
    "Is secretly poor despite appearances",
    "Has a hidden family",
    "Is a member of a secret organization",
    "Has made a deal with a dark power",
    "Witnessed something terrible",
    "Is hiding from someone",
    "Has a terminal illness",
    "Is planning something big",
    "Has betrayed someone close",
    "Possesses something valuable and dangerous",
    "Has unusual abilities they hide",
    "Killed someone",
    "Is being blackmailed",
    "Harbors forbidden beliefs"
  ],
  "quirks": [
    "Collects unusual items",
    "Has an unusual pet",
    "Follows strange superstitions",
    "Has peculiar eating habits",
    "Keeps a detailed journal",
    "Never sits with their back to a door",
    "Always carries a specific item",
    "Has an unusual sleep schedule",
    "Refuses to touch certain things",
    "Has elaborate grooming rituals",
    "Names their possessions",
    "Talks to themselves",
    "Has an unusual hobby",
    "Follows a strict routine",
    "Makes up words",
    "Has unusual taste in music/art",
    "Collects debts (or owes many)",
    "Never drinks alcohol (or always does)",
    "Has a nervous habit",
    "Believes in unusual conspiracy theories"
  ]
}
